<?xml version="1.0" encoding="UTF-8"?>
<database defaultPhpNamingMethod="underscore" heavyIndexing="false" name="propel" defaultIdMethod="native" package="lib.model" noXsd="true"><table skipSql="false" abstract="false" name="st_review" phpName="Review"><column primaryKey="false" required="false" autoIncrement="false" lazyLoad="false" name="created_at" type="timestamp"/><column primaryKey="false" required="false" autoIncrement="false" lazyLoad="false" name="updated_at" type="timestamp"/><column lazyLoad="false" name="id" type="INTEGER" primaryKey="true" required="true" autoIncrement="true"/><column primaryKey="false" autoIncrement="false" lazyLoad="false" name="order_id" type="INTEGER" required="false"/><column primaryKey="false" autoIncrement="false" lazyLoad="false" name="sf_guard_user_id" type="INTEGER" required="false"/><column primaryKey="false" autoIncrement="false" lazyLoad="false" name="product_id" type="INTEGER" required="true"/><column primaryKey="false" autoIncrement="false" lazyLoad="false" name="active" type="BOOLEAN" default="1" required="true"/><column primaryKey="false" required="false" autoIncrement="false" lazyLoad="false" name="score" type="INTEGER"/><column primaryKey="false" required="false" autoIncrement="false" lazyLoad="false" name="merchant" type="BOOLEAN"/><column primaryKey="false" required="false" autoIncrement="false" lazyLoad="false" name="admin_name" type="LONGVARCHAR"/><column primaryKey="false" required="false" autoIncrement="false" lazyLoad="false" name="admin_active" type="BOOLEAN"/><column primaryKey="false" required="false" autoIncrement="false" lazyLoad="false" name="anonymous" type="LONGVARCHAR"/><column primaryKey="false" autoIncrement="false" lazyLoad="false" name="agreement" type="BOOLEAN" default="0" required="true"/><column primaryKey="false" autoIncrement="false" lazyLoad="false" name="skipped" type="BOOLEAN" default="0" required="true"/><column primaryKey="false" required="false" autoIncrement="false" lazyLoad="false" name="order_number" type="VARCHAR" size="64"/><column primaryKey="false" required="false" autoIncrement="false" lazyLoad="false" name="description" type="LONGVARCHAR"/><column primaryKey="false" required="false" autoIncrement="false" lazyLoad="false" name="user_ip" type="VARCHAR" size="20"/><column primaryKey="false" required="false" autoIncrement="false" lazyLoad="false" name="username" type="VARCHAR" size="255"/><column primaryKey="false" required="false" autoIncrement="false" lazyLoad="false" name="language" type="VARCHAR" size="255"/><column primaryKey="false" required="false" autoIncrement="false" lazyLoad="false" name="is_pin_review" type="BOOLEAN" default="0"/><column primaryKey="false" required="false" autoIncrement="false" lazyLoad="false" name="pin_review" type="INTEGER" default="0"/><column primaryKey="false" required="false" autoIncrement="false" lazyLoad="false" name="user_picture" type="VARCHAR" size="255"/><column primaryKey="false" required="false" autoIncrement="false" lazyLoad="false" name="user_facebook" type="VARCHAR" size="255"/><column primaryKey="false" required="false" autoIncrement="false" lazyLoad="false" name="user_instagram" type="VARCHAR" size="255"/><column primaryKey="false" required="false" autoIncrement="false" lazyLoad="false" name="user_youtube" type="VARCHAR" size="255"/><column primaryKey="false" required="false" autoIncrement="false" lazyLoad="false" name="user_twitter" type="VARCHAR" size="255"/><column primaryKey="false" required="false" autoIncrement="false" lazyLoad="false" name="user_review_verified" type="BOOLEAN" default="0"/><foreign-key onUpdate="none" foreignTable="st_order" onDelete="cascade"><reference local="order_id" foreign="id"/></foreign-key><foreign-key onUpdate="none" foreignTable="sf_guard_user" onDelete="cascade"><reference local="sf_guard_user_id" foreign="id"/></foreign-key><foreign-key onUpdate="none" foreignTable="st_product" onDelete="cascade"><reference local="product_id" foreign="id"/></foreign-key></table><table skipSql="false" abstract="false" name="st_review_order" phpName="ReviewOrder"><column primaryKey="false" required="false" autoIncrement="false" lazyLoad="false" name="created_at" type="timestamp"/><column primaryKey="false" required="false" autoIncrement="false" lazyLoad="false" name="updated_at" type="timestamp"/><column lazyLoad="false" name="id" type="INTEGER" primaryKey="true" required="true" autoIncrement="true"/><column primaryKey="false" autoIncrement="false" lazyLoad="false" name="order_id" type="INTEGER" required="true"/><column primaryKey="false" required="false" autoIncrement="false" lazyLoad="false" name="order_number" type="VARCHAR" size="64"/><column primaryKey="false" autoIncrement="false" lazyLoad="false" name="sf_guard_user_id" type="INTEGER" required="true"/><column primaryKey="false" required="false" autoIncrement="false" lazyLoad="false" name="agreement" type="BOOLEAN"/><column primaryKey="false" required="false" autoIncrement="false" lazyLoad="false" name="mark" type="INTEGER"/><column primaryKey="false" required="false" autoIncrement="false" lazyLoad="false" name="active" type="BOOLEAN" default="0"/><column primaryKey="false" required="false" autoIncrement="false" lazyLoad="false" name="description" type="LONGVARCHAR"/><foreign-key onUpdate="none" foreignTable="st_order" onDelete="cascade"><reference local="order_id" foreign="id"/></foreign-key><foreign-key onUpdate="none" foreignTable="sf_guard_user" onDelete="cascade"><reference local="sf_guard_user_id" foreign="id"/></foreign-key></table><table skipSql="false" abstract="false" name="st_review_remind" phpName="ReviewRemind"><column primaryKey="false" required="false" autoIncrement="false" lazyLoad="false" name="created_at" type="timestamp"/><column primaryKey="false" required="false" autoIncrement="false" lazyLoad="false" name="updated_at" type="timestamp"/><column lazyLoad="false" name="id" type="INTEGER" primaryKey="true" required="true" autoIncrement="true"/><column primaryKey="false" required="false" autoIncrement="false" lazyLoad="false" name="title" type="VARCHAR" size="255"/><column primaryKey="false" required="false" autoIncrement="false" lazyLoad="false" name="text" type="LONGVARCHAR"/><column primaryKey="false" required="false" autoIncrement="false" lazyLoad="false" name="active" type="BOOLEAN"/></table></database>
