<?xml version="1.0" encoding="utf-8"?>
<xliff version="1.0">
	<file orginal="global" source-language="pl_PL" target-language="de" datatype="plaintext" date="2011-11-04T01:50:23Z">
		<body>
			<trans-unit id="1">
				<source>Nie masz wystarczających uprawnień aby oglądać tą stronę</source>
				<target>Sich verfügen nicht über die erforderlichen Rechte, um diese Seite anzuzeigen</target>
			</trans-unit>
			<trans-unit id="2">
				<source>Edytor grafiki</source>
				<target>Grafikeditor</target>
			</trans-unit>
			<trans-unit id="3">
				<source>Zaloguj się podając dane dostępowe do panelu administracyjnego.</source>
				<target>Melden Sie sich an, indem Sie die Zugangsdaten zum Administrationsbereich eingeben.</target>
			</trans-unit>
			<trans-unit id="4">
				<source>Użytkownik</source>
				<target>Benutzer</target>
			</trans-unit>
			<trans-unit id="5">
				<source>Hasło</source>
				<target>Kennwort</target>
			</trans-unit>
			<trans-unit id="6">
				<source>Zaloguj</source>
				<target>Anmelden</target>
			</trans-unit>
			<trans-unit id="7">
				<source>Proszę podać nazwę użytkownika</source>
				<target>Geben Sie den Benutzernamen ein</target>
			</trans-unit>
			<trans-unit id="8">
				<source>Proszę podać hasło</source>
				<target>Geben Sie das Kennwort ein</target>
			</trans-unit>
			<trans-unit id="9">
				<source>Proszę podać poprawną nazwę użytkownika i hasło</source>
				<target>Geben Sie den richtigen Benutzernamen und das richtige Kennwort ein</target>
			</trans-unit>
		</body>
	</file>
</xliff>