<?xml version="1.0" encoding="utf-8"?>
<xliff version="1.0">
    <file orginal="global" source-language="pl_PL" target-language="en_US" datatype="plaintext" date="2008-11-05T12:10:49Z">
        <body>
            <trans-unit id="1">
                <source>Start</source>
                <target>Start</target>
            </trans-unit>
            <trans-unit id="2">
                <source>Historia</source>
                <target>History</target>
            </trans-unit>
            <trans-unit id="3">
                <source>Historia oglądanych produktów</source>
                <target>History of viewed products</target>
            </trans-unit>
            <trans-unit id="4">
                <source>Ostatnio oglądane</source>
                <target>Last viewed</target>
            </trans-unit>
            <trans-unit id="5">
                <source>Koszyk</source>
                <target>Shopping cart</target>
            </trans-unit>
            <trans-unit id="6">
                <source>Potwierdzenie zamówienia</source>
                <target>Order confirmation</target>
            </trans-unit>
            <trans-unit id="7">
                <source>Podsumowanie zamówienia / Płatności</source>
                <target>Order summary / Payment</target>
            </trans-unit>
            <trans-unit id="8">
                <source>Szukaj</source>
                <target>Search</target>
            </trans-unit>
            <trans-unit id="9">
                <source>Podsumowanie zamówienia</source>
                <target>Order summary</target>
            </trans-unit>
            <trans-unit id="10">
                <source>Płatność</source>
                <target>Payment</target>
            </trans-unit>
        </body>
    </file>
</xliff>